connexion/__init__.py
connexion/__main__.py
connexion/cli.py
connexion/exceptions.py
connexion/handlers.py
connexion/http_facts.py
connexion/json_schema.py
connexion/jsonifier.py
connexion/lifecycle.py
connexion/mock.py
connexion/options.py
connexion/problem.py
connexion/resolver.py
connexion/spec.py
connexion/utils.py
connexion/apis/__init__.py
connexion/apis/abstract.py
connexion/apis/aiohttp_api.py
connexion/apis/flask_api.py
connexion/apis/flask_utils.py
connexion/apps/__init__.py
connexion/apps/abstract.py
connexion/apps/aiohttp_app.py
connexion/apps/flask_app.py
connexion/decorators/__init__.py
connexion/decorators/coroutine_wrappers.py
connexion/decorators/decorator.py
connexion/decorators/metrics.py
connexion/decorators/parameter.py
connexion/decorators/produces.py
connexion/decorators/response.py
connexion/decorators/uri_parsing.py
connexion/decorators/validation.py
connexion/operations/__init__.py
connexion/operations/abstract.py
connexion/operations/compat.py
connexion/operations/openapi.py
connexion/operations/secure.py
connexion/operations/swagger2.py
connexion/security/__init__.py
connexion/security/aiohttp_security_handler_factory.py
connexion/security/async_security_handler_factory.py
connexion/security/flask_security_handler_factory.py
connexion/security/security_handler_factory.py
lcdp_connexion-2.9.4.dist-info/LICENSE.txt
lcdp_connexion-2.9.4.dist-info/METADATA
lcdp_connexion-2.9.4.dist-info/WHEEL
lcdp_connexion-2.9.4.dist-info/entry_points.txt
lcdp_connexion-2.9.4.dist-info/top_level.txt
lcdp_connexion-2.9.4.dist-info/RECORD
