Metadata-Version: 2.1
Name: lcdp-connexion
Version: 2.9.4
Summary: LCDP Connexion - API first applications with OpenAPI/Swagger and Flask
Home-page: https://github.com/zalando/connexion
Author: Zalando SE
License: Apache License Version 2.0
Keywords: openapi oai swagger rest api oauth flask microservice framework
Platform: UNKNOWN
Classifier: Programming Language :: Python
Classifier: Programming Language :: Python :: 3.6
Classifier: Programming Language :: Python :: 3.7
Classifier: Programming Language :: Python :: 3.8
Classifier: Development Status :: 5 - Production/Stable
Classifier: Intended Audience :: Developers
Classifier: Operating System :: OS Independent
Classifier: Topic :: Internet :: WWW/HTTP :: WSGI :: Application
Classifier: Topic :: Software Development :: Libraries :: Application Frameworks
Requires-Python: >=3.6
License-File: LICENSE.txt
Requires-Dist: clickclick (<21,>=1.2)
Requires-Dist: jsonschema (<4,>=2.5.1)
Requires-Dist: PyYAML (<6,>=5.1)
Requires-Dist: requests (<3,>=2.9.1)
Requires-Dist: inflection (<0.6,>=0.3.1)
Requires-Dist: openapi-spec-validator (<0.4,>=0.2.4)
Requires-Dist: werkzeug (<3,>=1.0)
Requires-Dist: flask (<3,>=1.0.4)
Provides-Extra: aiohttp
Requires-Dist: aiohttp (<4,>=2.3.10) ; extra == 'aiohttp'
Requires-Dist: aiohttp-jinja2 (<2,>=0.14.0) ; extra == 'aiohttp'
Provides-Extra: docs
Requires-Dist: sphinx-autoapi (==1.8.1) ; extra == 'docs'
Provides-Extra: flask
Requires-Dist: flask (<3,>=1.0.4) ; extra == 'flask'
Provides-Extra: swagger-ui
Requires-Dist: swagger-ui-bundle (<0.1,>=0.0.2) ; extra == 'swagger-ui'
Provides-Extra: tests
Requires-Dist: decorator (<6,>=5) ; extra == 'tests'
Requires-Dist: pytest (<7,>=6) ; extra == 'tests'
Requires-Dist: pytest-cov (<3,>=2) ; extra == 'tests'
Requires-Dist: testfixtures (<7,>=6) ; extra == 'tests'
Requires-Dist: flask (<3,>=1.0.4) ; extra == 'tests'
Requires-Dist: swagger-ui-bundle (<0.1,>=0.0.2) ; extra == 'tests'
Requires-Dist: aiohttp (<4,>=2.3.10) ; extra == 'tests'
Requires-Dist: aiohttp-jinja2 (<2,>=0.14.0) ; extra == 'tests'
Requires-Dist: pytest-aiohttp ; extra == 'tests'
Requires-Dist: aiohttp-remotes ; extra == 'tests'
